cli/__init__.py
cli/cli.py
cli/utils.py
cli/commands/__init__.py
cli/commands/auth.py
cli/commands/bbs.py
cli/commands/messaging.py
cli/commands/services.py
cli/commands/social.py
cli/commands/test.py
cli/commands/unsocial.py
cli/commands/users.py
cli_social-0.0.4.dev0.dist-info/METADATA
cli_social-0.0.4.dev0.dist-info/WHEEL
cli_social-0.0.4.dev0.dist-info/entry_points.txt
cli_social-0.0.4.dev0.dist-info/top_level.txt
cli_social-0.0.4.dev0.dist-info/RECORD
