Metadata-Version: 2.4
Name: cli-social
Version: 0.0.4.dev0
Summary: A CLI interface for interacting with the MinakiLabs Social API
Home-page: https://minakilabs.dev
Author: Andrew Polykandriotis
Author-email: andrew@minakilabs.com
Project-URL: Source, https://github.com/minakilabs/cli-social
Classifier: Development Status :: 3 - Alpha
Classifier: Intended Audience :: Developers
Classifier: Topic :: Software Development :: Build Tools
Classifier: License :: Other/Proprietary License
Classifier: Programming Language :: Python :: 3
Requires-Python: >=3.7
Requires-Dist: click
Requires-Dist: requests
Requires-Dist: fastapi
Requires-Dist: uvicorn
Requires-Dist: sqlalchemy
Requires-Dist: asyncpg
Dynamic: author
Dynamic: author-email
Dynamic: classifier
Dynamic: description
Dynamic: description-content-type
Dynamic: home-page
Dynamic: project-url
Dynamic: requires-dist
Dynamic: requires-python
Dynamic: summary
